{
	"nodeModulesDir": "auto",
	"imports": {
		"$/": "./src/",
		"@tanstack/query-core": "npm:@tanstack/query-core"
	},
	"lint": {
		"rules": {
			"exclude": [
				"no-sloppy-imports"
			]
		}
	},
	"tasks": {
		"dev": "vite dev",
		"build": "vite build",
		"preview": "vite preview",
		"install": "deno install",
		"test": "deno test -A --no-check src/collections/networks.spec.ts src/collections/coins.spec.ts src/lib/voltaire.spec.ts",
		"test:unit": "deno test -A --no-check src/collections/networks.spec.ts src/collections/coins.spec.ts src/lib/voltaire.spec.ts",
		"test:e2e": "node node_modules/@playwright/test/cli.js test"
	}
}
